{"puzzle_type": "crossword", "data": {"width": 5, "height": 5, "empties": [19, 23, 24], "labels": [[0, "1"], [1, "2"], [2, "3"], [3, "4"], [4, "5"], [5, "6"], [10, "7"], [15, "8"], [20, "9"]], "clues": {"across": [{"label": "1", "text": "Beach trees"}, {"label": "6", "text": "Beach view"}, {"label": "7", "text": "Beach keepsake"}, {"label": "8", "text": "Removed, as wrapping paper"}, {"label": "9", "text": "What miso paste is made from"}], "down": [{"label": "1", "text": "Feed fillers"}, {"label": "2", "text": "Sound before a blessing"}, {"label": "3", "text": "Cautious"}, {"label": "4", "text": "Like seahorses that give birth"}, {"label": "5", "text": "Show for Sarah Silverman and Sarah Sherman, for short"}]}}}