{"puzzle_type": "crossword", "data": {"width": 5, "height": 5, "empties": [20, 24], "labels": [[0, "1"], [1, "2"], [2, "3"], [3, "4"], [4, "5"], [5, "6"], [10, "7"], [15, "8"], [21, "9"]], "clues": {"across": [{"label": "1", "text": "\"Pointer\" used to highlight a talking point"}, {"label": "6", "text": "Submit a C.V."}, {"label": "7", "text": "Get behind the wheel"}, {"label": "8", "text": "\"Oh boy, that's not good!\""}, {"label": "9", "text": "\"___ Mis\u00e9rables\""}], "down": [{"label": "1", "text": "\"___ Madonna\" (Beatles song)"}, {"label": "2", "text": "When March Madness ends, curiously"}, {"label": "3", "text": "Sudden increase"}, {"label": "4", "text": "Legolas and Galadriel, in \"The Lord of the Rings\""}, {"label": "5", "text": "Spirits akin to bourbons"}]}}}